{
    "nomSimulacio": "G060_S002",
    "ubicacioSimulacio": "D:/Documentos/TDR-Simulacio/TDR/Builds/006 - 13.11.2022/TDR_Data\\Simulacions\\Experiment\\Grup_060\\G060_S002.json",
    "dataCreacio": "13/11/2022 22:45:01",
    "probabilitatMutacio": 60.44482421875,
    "tempsMaxim": 1200.0,
    "tempsTotal": 1200.002685546875,
    "randomSeed": 32,
    "individusPerFerApareixerNormal": [
        10,
        0,
        0,
        30,
        0,
        0,
        0,
        0,
        0,
        0
    ],
    "individusPerFerApareixerPersonalitzat": [
        0,
        0,
        0,
        0,
        0,
        0,
        0,
        0,
        0,
        0,
        0,
        0,
        0,
        0,
        0,
        0,
        0,
        0,
        0,
        0,
        0,
        0,
        0,
        0,
        0,
        0,
        0,
        0,
        0,
        0
    ],
    "notificacions": [
        {
            "tipus": 0,
            "text": "00:00 - Inicia la simulació."
        },
        {
            "tipus": 5,
            "text": "00:30 - S'infecta el primer conill."
        },
        {
            "tipus": 5,
            "text": "09:41 - S'infecta el primer humà."
        },
        {
            "tipus": 3,
            "text": "20:00 - La simulació arriba al temps màxim establert per l'usuari."
        }
    ],
    "finalitzada": true,
    "dades": {
        "especiesNormals": [
            {
                "id": 0,
                "nom": "Humà",
                "nombreIndividus": [
                    10,
                    10,
                    10,
                    10,
                    10,
                    10,
                    10,
                    10,
                    10,
                    10,
                    10,
                    10,
                    10,
                    10,
                    10,
                    10,
                    10,
                    10,
                    10,
                    13,
                    15,
                    15,
                    15,
                    15,
                    15,
                    15,
                    15,
                    11,
                    10,
                    8,
                    8,
                    7,
                    7,
                    6,
                    6,
                    5,
                    5,
                    5,
                    7,
                    7
                ],
                "nombreIndividusInfectats": [
                    0,
                    0,
                    0,
                    0,
                    0,
                    0,
                    0,
                    0,
                    0,
                    0,
                    0,
                    0,
                    0,
                    0,
                    0,
                    0,
                    0,
                    0,
                    0,
                    0,
                    3,
                    5,
                    7,
                    7,
                    8,
                    8,
                    8,
                    5,
                    5,
                    3,
                    3,
                    2,
                    2,
                    1,
                    1,
                    0,
                    0,
                    0,
                    0,
                    0
                ],
                "percentatgeInfectats": [
                    0.0,
                    0.0,
                    0.0,
                    0.0,
                    0.0,
                    0.0,
                    0.0,
                    0.0,
                    0.0,
                    0.0,
                    0.0,
                    0.0,
                    0.0,
                    0.0,
                    0.0,
                    0.0,
                    0.0,
                    0.0,
                    0.0,
                    0.0,
                    20.0,
                    33.333335876464847,
                    46.66666793823242,
                    46.66666793823242,
                    53.333335876464847,
                    53.333335876464847,
                    53.333335876464847,
                    45.45454788208008,
                    50.0,
                    37.5,
                    37.5,
                    28.571430206298829,
                    28.571430206298829,
                    16.666667938232423,
                    16.666667938232423,
                    0.0,
                    0.0,
                    0.0,
                    0.0,
                    0.0
                ],
                "salutMitjana": [
                    0.0,
                    0.0,
                    0.0,
                    0.0,
                    0.0,
                    0.0,
                    0.0,
                    0.0,
                    0.0,
                    0.0,
                    0.0,
                    0.0,
                    0.0,
                    0.0,
                    0.0,
                    0.0,
                    0.0,
                    0.0,
                    0.0,
                    0.059701643884181979,
                    0.051741424947977069,
                    0.051741424947977069,
                    0.051741424947977069,
                    0.051741424947977069,
                    0.051741424947977069,
                    0.051741424947977069,
                    0.051741424947977069,
                    0.07055649161338806,
                    0.07761213928461075,
                    0.09701517224311829,
                    0.09701517224311829,
                    0.1108744814991951,
                    0.1108744814991951,
                    0.1293535679578781,
                    0.1293535679578781,
                    0.1552242785692215,
                    0.1552242785692215,
                    0.1552242785692215,
                    0.1466538906097412,
                    0.1466538906097412
                ]
            },
            {
                "id": 1,
                "nom": "Gallina",
                "nombreIndividus": [
                    0,
                    0,
                    0,
                    0,
                    0,
                    0,
                    0,
                    0,
                    0,
                    0,
                    0,
                    0,
                    0,
                    0,
                    0,
                    0,
                    0,
                    0,
                    0,
                    0,
                    0,
                    0,
                    0,
                    0,
                    0,
                    0,
                    0,
                    0,
                    0,
                    0,
                    0,
                    0,
                    0,
                    0,
                    0,
                    0,
                    0,
                    0,
                    0,
                    0
                ],
                "nombreIndividusInfectats": [
                    0,
                    0,
                    0,
                    0,
                    0,
                    0,
                    0,
                    0,
                    0,
                    0,
                    0,
                    0,
                    0,
                    0,
                    0,
                    0,
                    0,
                    0,
                    0,
                    0,
                    0,
                    0,
                    0,
                    0,
                    0,
                    0,
                    0,
                    0,
                    0,
                    0,
                    0,
                    0,
                    0,
                    0,
                    0,
                    0,
                    0,
                    0,
                    0,
                    0
                ],
                "percentatgeInfectats": [
                    NaN,
                    NaN,
                    NaN,
                    NaN,
                    NaN,
                    NaN,
                    NaN,
                    NaN,
                    NaN,
                    NaN,
                    NaN,
                    NaN,
                    NaN,
                    NaN,
                    NaN,
                    NaN,
                    NaN,
                    NaN,
                    NaN,
                    NaN,
                    NaN,
                    NaN,
                    NaN,
                    NaN,
                    NaN,
                    NaN,
                    NaN,
                    NaN,
                    NaN,
                    NaN,
                    NaN,
                    NaN,
                    NaN,
                    NaN,
                    NaN,
                    NaN,
                    NaN,
                    NaN,
                    NaN,
                    NaN
                ],
                "salutMitjana": []
            },
            {
                "id": 2,
                "nom": "Guineu",
                "nombreIndividus": [
                    0,
                    0,
                    0,
                    0,
                    0,
                    0,
                    0,
                    0,
                    0,
                    0,
                    0,
                    0,
                    0,
                    0,
                    0,
                    0,
                    0,
                    0,
                    0,
                    0,
                    0,
                    0,
                    0,
                    0,
                    0,
                    0,
                    0,
                    0,
                    0,
                    0,
                    0,
                    0,
                    0,
                    0,
                    0,
                    0,
                    0,
                    0,
                    0,
                    0
                ],
                "nombreIndividusInfectats": [
                    0,
                    0,
                    0,
                    0,
                    0,
                    0,
                    0,
                    0,
                    0,
                    0,
                    0,
                    0,
                    0,
                    0,
                    0,
                    0,
                    0,
                    0,
                    0,
                    0,
                    0,
                    0,
                    0,
                    0,
                    0,
                    0,
                    0,
                    0,
                    0,
                    0,
                    0,
                    0,
                    0,
                    0,
                    0,
                    0,
                    0,
                    0,
                    0,
                    0
                ],
                "percentatgeInfectats": [
                    NaN,
                    NaN,
                    NaN,
                    NaN,
                    NaN,
                    NaN,
                    NaN,
                    NaN,
                    NaN,
                    NaN,
                    NaN,
                    NaN,
                    NaN,
                    NaN,
                    NaN,
                    NaN,
                    NaN,
                    NaN,
                    NaN,
                    NaN,
                    NaN,
                    NaN,
                    NaN,
                    NaN,
                    NaN,
                    NaN,
                    NaN,
                    NaN,
                    NaN,
                    NaN,
                    NaN,
                    NaN,
                    NaN,
                    NaN,
                    NaN,
                    NaN,
                    NaN,
                    NaN,
                    NaN,
                    NaN
                ],
                "salutMitjana": []
            },
            {
                "id": 3,
                "nom": "Conill",
                "nombreIndividus": [
                    30,
                    30,
                    30,
                    30,
                    30,
                    30,
                    76,
                    76,
                    74,
                    57,
                    45,
                    56,
                    96,
                    75,
                    65,
                    63,
                    56,
                    113,
                    108,
                    94,
                    84,
                    75,
                    78,
                    152,
                    148,
                    140,
                    127,
                    126,
                    170,
                    124,
                    94,
                    67,
                    24,
                    9,
                    8,
                    9,
                    9,
                    5,
                    5,
                    5
                ],
                "nombreIndividusInfectats": [
                    0,
                    0,
                    2,
                    10,
                    13,
                    17,
                    53,
                    65,
                    72,
                    56,
                    44,
                    40,
                    82,
                    72,
                    63,
                    61,
                    54,
                    61,
                    92,
                    86,
                    76,
                    67,
                    61,
                    95,
                    118,
                    124,
                    121,
                    116,
                    120,
                    95,
                    76,
                    56,
                    20,
                    8,
                    7,
                    6,
                    6,
                    3,
                    3,
                    3
                ],
                "percentatgeInfectats": [
                    0.0,
                    0.0,
                    6.6666669845581059,
                    33.333335876464847,
                    43.33333206176758,
                    56.66666793823242,
                    69.73684692382813,
                    85.52631378173828,
                    97.29730224609375,
                    98.24561309814453,
                    97.77777862548828,
                    71.42857360839844,
                    85.41667175292969,
                    96.0,
                    96.92308044433594,
                    96.82539367675781,
                    96.42857360839844,
                    53.9822998046875,
                    85.18518829345703,
                    91.48936462402344,
                    90.47618865966797,
                    89.33332824707031,
                    78.20512390136719,
                    62.5,
                    79.72972869873047,
                    88.57142639160156,
                    95.27558898925781,
                    92.06349182128906,
                    70.5882339477539,
                    76.61289978027344,
                    80.85106658935547,
                    83.58209228515625,
                    83.33332824707031,
                    88.8888931274414,
                    87.5,
                    66.66667175292969,
                    66.66667175292969,
                    60.000003814697269,
                    60.000003814697269,
                    60.000003814697269
                ],
                "salutMitjana": [
                    0.0,
                    0.0,
                    0.0,
                    0.0,
                    0.0,
                    0.0,
                    -0.0599064938724041,
                    -0.0599064938724041,
                    -0.05115358904004097,
                    0.01487983949482441,
                    0.06492798775434494,
                    0.04729381948709488,
                    0.02600250206887722,
                    0.03328320011496544,
                    0.0785219594836235,
                    0.09927979111671448,
                    0.14440305531024934,
                    0.09184020757675171,
                    0.09740138053894043,
                    0.11137998104095459,
                    0.18108700215816499,
                    0.216989666223526,
                    0.29745736718177798,
                    0.24631042778491975,
                    0.258385568857193,
                    0.26911115646362307,
                    0.2919056713581085,
                    0.3251078426837921,
                    0.341105192899704,
                    0.29486119747161868,
                    0.2763681709766388,
                    0.3109687864780426,
                    0.3986983299255371,
                    0.4417962431907654,
                    0.5117831826210022,
                    0.4819900095462799,
                    0.4819900095462799,
                    0.5509122610092163,
                    0.5509122610092163,
                    0.5509122610092163
                ]
            }
        ],
        "especiesPersonalitzades": [
            {
                "id": 0,
                "nom": "IR-N",
                "nombreIndividus": [
                    0,
                    0,
                    0,
                    0,
                    0,
                    0,
                    0,
                    0,
                    0,
                    0,
                    0,
                    0,
                    0,
                    0,
                    0,
                    0,
                    0,
                    0,
                    0,
                    0,
                    0,
                    0,
                    0,
                    0,
                    0,
                    0,
                    0,
                    0,
                    0,
                    0,
                    0,
                    0,
                    0,
                    0,
                    0,
                    0,
                    0,
                    0,
                    0,
                    0
                ],
                "nombreIndividusInfectats": [
                    0,
                    0,
                    0,
                    0,
                    0,
                    0,
                    0,
                    0,
                    0,
                    0,
                    0,
                    0,
                    0,
                    0,
                    0,
                    0,
                    0,
                    0,
                    0,
                    0,
                    0,
                    0,
                    0,
                    0,
                    0,
                    0,
                    0,
                    0,
                    0,
                    0,
                    0,
                    0,
                    0,
                    0,
                    0,
                    0,
                    0,
                    0,
                    0,
                    0
                ],
                "percentatgeInfectats": [
                    NaN,
                    NaN,
                    NaN,
                    NaN,
                    NaN,
                    NaN,
                    NaN,
                    NaN,
                    NaN,
                    NaN,
                    NaN,
                    NaN,
                    NaN,
                    NaN,
                    NaN,
                    NaN,
                    NaN,
                    NaN,
                    NaN,
                    NaN,
                    NaN,
                    NaN,
                    NaN,
                    NaN,
                    NaN,
                    NaN,
                    NaN,
                    NaN,
                    NaN,
                    NaN,
                    NaN,
                    NaN,
                    NaN,
                    NaN,
                    NaN,
                    NaN,
                    NaN,
                    NaN,
                    NaN,
                    NaN
                ],
                "salutMitjana": []
            }
        ]
    }
}